{
  "type": "FeatureCollection",
  "features": [
    {
      "type": "Feature",
      "geometry": {
        "type": "Point",
        "coordinates": [
          15.361342,
          67.391338
        ]
      },
      "properties": {
        "navn": "VALNESFJORD HELSESPORTSSENTER STI",
        "type": "Detaljhandel med bredt vareutvalg med hovedvekt på nærings- og nytelsesmidler",
        "adresse": "Østerkløftveien 249, 8215"
      }
    }
  ]
}