{
  "type": "FeatureCollection",
  "features": [
    {
      "type": "Feature",
      "geometry": {
        "type": "Point",
        "coordinates": [
          5.7317091,
          58.9709041
        ]
      },
      "properties": {
        "navn": "MATS STANGELAND",
        "type": "Detaljhandel med kulturvarer ikke nevnt annet sted",
        "adresse": "Legekontorene Skagen 12, 4006"
      }
    }
  ]
}