{
  "type": "FeatureCollection",
  "features": [
    {
      "type": "Feature",
      "geometry": {
        "type": "Point",
        "coordinates": [
          10.82001,
          59.846002
        ]
      },
      "properties": {
        "navn": "LENSAPPLY AS",
        "type": "Industri-, produkt- og motedesignvirksomhet",
        "adresse": "Jordstjerneveien 79D, 1283"
      }
    }
  ]
}